pystac_generator-0.3.31.dist-info/METADATA
pystac_generator-0.3.31.dist-info/WHEEL
pystac_generator-0.3.31.dist-info/entry_points.txt
pystac_generator-0.3.31.dist-info/licenses/LICENSE
stac_generator/__init__.py
stac_generator/__main__.py
stac_generator/__version__.py
stac_generator/_types.py
stac_generator/core/__init__.py
stac_generator/core/base/__init__.py
stac_generator/core/base/generator.py
stac_generator/core/base/schema.py
stac_generator/core/base/utils.py
stac_generator/core/point/__init__.py
stac_generator/core/point/generator.py
stac_generator/core/point/schema.py
stac_generator/core/raster/__init__.py
stac_generator/core/raster/generator.py
stac_generator/core/raster/schema.py
stac_generator/core/vector/__init__.py
stac_generator/core/vector/generator.py
stac_generator/core/vector/schema.py
stac_generator/exceptions.py
stac_generator/factory.py
stac_generator/py.typed
pystac_generator-0.3.31.dist-info/RECORD
