Metadata-Version: 2.1
Name: pystac-generator
Version: 0.3.31
Summary: A python package and CLI tool for generating STAC catalog from spatial data files
Keywords: stac,generator,stac-generator
Author-Email: Joseph Sclauzero <joseph.sclauzero@adelaide.edu.au>
License: MIT
Project-URL: repository, https://github.com/JosephUoA/stac-generator
Requires-Python: >=3.11
Requires-Dist: pystac>=1.10.1
Requires-Dist: jsonschema>=4.23.0
Requires-Dist: rasterio>=1.4.1
Requires-Dist: geopandas>=1.0.1
Requires-Dist: httpx>=0.27.2
Requires-Dist: stac-pydantic>=3.1.2
Requires-Dist: fiona>=1.10.1
Requires-Dist: timezonefinder>=6.5.5
Requires-Dist: click>=8.1.8
Requires-Dist: rich-argparse>=1.7.0
Requires-Dist: pyyaml>=6.0.2
